fixout/__init__.py
fixout/artifact.py
fixout/fairness.py
fixout/helper.py
fixout/runner.py
fixout/utils.py
fixout/demos/demo_data.py
fixout/demos/data/adult.data
fixout/demos/data/bank.data
fixout/demos/data/comcrime.data
fixout/demos/data/compas.data
fixout/demos/data/default.data
fixout/demos/data/german.data
fixout/demos/data/hmda.data
fixout/demos/data/lsac.data
fixout/demos/data/nypd-sqf-2017.data
fixout/interface/FixOut.py
fixout/interface/__init__.py
fixout/interface/constants.py
fixout/interface/ttypes.py
fixout/web/__init__.py
fixout/web/dataset.py
fixout/web/fair_exp.py
fixout/web/webapp.py
fixout/web/static/fixout.png
fixout/web/static/fixout2.png
fixout/web/static/fixout_3.png
fixout/web/static/fixout_grey.png
fixout/web/static/iso-2.svg
fixout/web/static/iso.png
fixout/web/static/pfixout.png
fixout/web/static/selectbox.css
fixout/web/static/style.css
fixout/web/static/style.old.css
fixout/web/templates/base.html
fixout/web/templates/base_data.html
fixout/web/templates/base_metrics.html
fixout/web/templates/correlation.html
fixout/web/templates/error.html
fixout/web/templates/histograms.html
fixout/web/templates/index.html
fixout/web/templates/metrics.html
fixout/web/templates/premium.html
fixout/web/templates/reversed.html
fixout/web/templates/visualization.html
fixout/web/templates/utils-web/imports.html
fixout/web/templates/utils-web/scripts.html
fixout-0.1.35.dist-info/licenses/LICENSE
fixout-0.1.35.dist-info/METADATA
fixout-0.1.35.dist-info/WHEEL
fixout-0.1.35.dist-info/top_level.txt
fixout-0.1.35.dist-info/RECORD
