Metadata-Version: 2.4
Name: fixout
Version: 0.1.35
Summary: Algorithmic inspection for trustworthy ML models
Home-page: https://github.com/fixouttech/fixout
Author: FixOut
License: BSD
Classifier: License :: OSI Approved :: BSD License
Classifier: Programming Language :: Python :: 3.12
Classifier: Programming Language :: Python :: 3.13
Classifier: Programming Language :: Python :: 3.9
Classifier: Programming Language :: Python :: 3.8
Classifier: Operating System :: OS Independent
Requires-Python: >=3.8
License-File: LICENSE
Requires-Dist: Flask>=3.0.3
Requires-Dist: Jinja2>=3.1.4
Requires-Dist: numpy>=1.26.4
Requires-Dist: pandas>=2.2.2
Requires-Dist: plotly>=5.24.0
Requires-Dist: scikit-image>=0.24.0
Requires-Dist: scikit-learn>=1.5.2
Requires-Dist: scipy>=1.11.4
Requires-Dist: thrift>=0.20.0
Requires-Dist: tinycss2>=1.4.0
Requires-Dist: webcolors>=24.11.1
Dynamic: author
Dynamic: classifier
Dynamic: description
Dynamic: description-content-type
Dynamic: home-page
Dynamic: license
Dynamic: license-file
Dynamic: requires-dist
Dynamic: requires-python
Dynamic: summary
